drtransformer/__init__.py
drtransformer/drtransformer.py
drtransformer/landscape.py
drtransformer/linalg.py
drtransformer/plotting.py
drtransformer/rnafolding.py
drtransformer/utils.py
drtransformer-1.0.dist-info/entry_points.txt
drtransformer-1.0.dist-info/LICENSE
drtransformer-1.0.dist-info/WHEEL
drtransformer-1.0.dist-info/METADATA
drtransformer-1.0.dist-info/RECORD
