Metadata-Version: 2.1
Name: drtransformer
Version: 1.0
Summary: Heuristic cotranscriptional folding using the nearest neighbor energy model.
Keywords: cotranscriptional folding,RNA,secondary structure
Author-email: Stefan Badelt <bad-ants-fleet@posteo.eu>
Requires-Python: >=3.8
Classifier: Intended Audience :: Science/Research
Classifier: Programming Language :: Python :: 3.8
Classifier: Programming Language :: Python :: 3.9
Classifier: Programming Language :: Python :: 3.10
Classifier: Programming Language :: Python :: 3.11
Classifier: License :: OSI Approved :: MIT License
Classifier: Development Status :: 5 - Production/Stable
Classifier: Topic :: Scientific/Engineering :: Bio-Informatics
Requires-Dist: packaging
Requires-Dist: numpy
Requires-Dist: scipy
Requires-Dist: matplotlib
Requires-Dist: pytest ; extra == "dev"
Project-URL: Home, https://github.com/ViennaRNA/drtransformer
Provides-Extra: dev
